{
  "id": 21056,
  "name": "追逐风的时候",
  "star": 4,
  "desc": "<i>「呵，这颗给小倒霉蛋，总能堵上她那欠债爸妈的嘴了吧，少打她几顿也好。<br />「这颗给卖酸瓜糖的老奶奶救急，小病小痛都得治了，我可不想哪天吃不到那么好的糖……」</i><br /><br />女孩猫着腰一颗颗地细数布袋里的珠宝，忽然打了个喷嚏。<br /><i>「谁在想我？」</i><br /><br /><i>「赛法利娅，你在这儿呐。」</i><br />丝线盘绕在她的身后，似乎正犹豫着从哪儿开始。<br /><br /><i>「以后，追逐风的时候……」</i><br />冰冷的金丝缠绕在她的手腕，令她动弹不得。<br /><br /><i>「也别忘了照顾好自己。」</i><br /><br />她逃向远方，回头才发现，那斗篷绽线的一角，已被缝补如新。",
  "type": "同谐",
  "typeId": 0,
  "baseAttr": {
    "atk": 476.28,
    "hp": 1058.4,
    "def": 396.9
  },
  "growAttr": {
    "atk": 3.24,
    "hp": 7.2,
    "def": 2.7
  },
  "attr": {
    "0": {
      "promote": 0,
      "maxLevel": 20,
      "cost": {
        "29328": 4000,
        "3517880": 5
      },
      "attrs": {
        "atk": 21.6,
        "hp": 48,
        "def": 18
      }
    },
    "1": {
      "promote": 1,
      "maxLevel": 30,
      "cost": {
        "29328": 8000,
        "874346": 3,
        "3517880": 10
      },
      "attrs": {
        "atk": 47.52,
        "hp": 105.6,
        "def": 39.6
      }
    },
    "2": {
      "promote": 2,
      "maxLevel": 40,
      "cost": {
        "29328": 16000,
        "589819": 3,
        "3276614": 6
      },
      "attrs": {
        "atk": 82.08,
        "hp": 182.4,
        "def": 68.4
      }
    },
    "3": {
      "promote": 3,
      "maxLevel": 50,
      "cost": {
        "29328": 40000,
        "589819": 6,
        "3276614": 9
      },
      "attrs": {
        "atk": 116.64,
        "hp": 259.2,
        "def": 97.2
      }
    },
    "4": {
      "promote": 4,
      "maxLevel": 60,
      "cost": {
        "29328": 80000,
        "673760": 4,
        "3526997": 5
      },
      "attrs": {
        "atk": 151.2,
        "hp": 336,
        "def": 126
      }
    },
    "5": {
      "promote": 5,
      "maxLevel": 70,
      "cost": {
        "29328": 160000,
        "673760": 8,
        "3526997": 7
      },
      "attrs": {
        "atk": 185.76,
        "hp": 412.8,
        "def": 154.8
      }
    },
    "6": {
      "promote": 6,
      "maxLevel": 80,
      "cost": {},
      "attrs": {
        "atk": 220.32,
        "hp": 489.6,
        "def": 183.6
      }
    }
  },
  "skill": {
    "id": 21056,
    "name": "慌张",
    "desc": "进入战斗后，使我方全体造成的击破伤害提高<nobr>$1[i]%</nobr>。同类技能无法重复生效。",
    "tables": {
      "1": [
        16,
        18,
        20,
        22,
        24
      ]
    }
  }
}